__init__.py
__main__.py
agents/__init__.py
agents/city.py
agents/province.py
core/__init__.py
core/algorithms.py
core/data_loaders.py
core/payoff.py
docs/ODD+D.md
model/__init__.py
model/main.py
cwatqim-0.1.6.dist-info/METADATA
cwatqim-0.1.6.dist-info/WHEEL
cwatqim-0.1.6.dist-info/RECORD
