Metadata-Version: 2.4
Name: cwatqim
Version: 0.1.6
Summary: Crop-Water Quota Irrigation Model - ABM for Yellow River water allocation
Project-URL: Homepage, https://github.com/SongshGeoLab/CWatQIM
Project-URL: Documentation, https://github.com/SongshGeoLab/CWatQIM#readme
Project-URL: Repository, https://github.com/SongshGeoLab/CWatQIM
Project-URL: Issues, https://github.com/SongshGeoLab/CWatQIM/issues
Project-URL: Changelog, https://github.com/SongshGeoLab/CWatQIM/blob/main/CHANGELOG.md
Project-URL: DOI, https://doi.org/10.5281/zenodo.4305038
Author-email: Shuang Song <songshgeo@gmail.com>
License: MIT
Keywords: ABM,Yellow River,agent-based model,hydrology,irrigation,water quota,water resources
Classifier: Development Status :: 4 - Beta
Classifier: Intended Audience :: Science/Research
Classifier: License :: OSI Approved :: MIT License
Classifier: Programming Language :: Python :: 3.11
Classifier: Topic :: Scientific/Engineering :: Hydrology
Requires-Python: <3.12,>=3.11
Requires-Dist: abses>=0.9.4
Requires-Dist: aquacrop-abses>=0.5.1
Requires-Dist: fiona>=1.9
Requires-Dist: geopandas>=0.14
Requires-Dist: hydra-core>=1.3
Requires-Dist: networkx>=3.0
Requires-Dist: numpy<2.2,>=1.24
Requires-Dist: pandas>=2.0
Requires-Dist: rasterio>=1.3
Requires-Dist: rioxarray>=0.13
Requires-Dist: xarray>=2023.1.0
Provides-Extra: dev
Requires-Dist: ipykernel>=6.21.2; extra == 'dev'
Requires-Dist: jupyterlab<5.0,>4.0; extra == 'dev'
Requires-Dist: pytest>=7.2.1; extra == 'dev'
